{
  "updated": "2026-04-20",
  "strategies": [
    {
      "id": "S1",
      "name": "原版雙動能",
      "pick": "VXUS",
      "assets": [
        "VOO",
        "VXUS",
        "BND",
        "BIL"
      ],
      "mode": "intl",
      "modeLabel": "外國股市"
    },
    {
      "id": "S2",
      "name": "原版雙動能 · 拉風增強版",
      "pick": "QQQ",
      "assets": [
        "QQQ",
        "VXUS",
        "BND",
        "BIL"
      ],
      "mode": "attack",
      "modeLabel": "美國股市"
    },
    {
      "id": "S3",
      "name": "加速雙動能",
      "pick": "VSS",
      "assets": [
        "VOO",
        "VSS",
        "TLT",
        "BIL"
      ],
      "mode": "intl",
      "modeLabel": "進攻 +9.18%"
    },
    {
      "id": "S4",
      "name": "騷速雙動能 · 含 QQQ",
      "pick": "VSS",
      "assets": [
        "QQQ",
        "VSS",
        "TLT",
        "BIL"
      ],
      "mode": "intl",
      "modeLabel": "進攻 +9.18%"
    },
    {
      "id": "S5",
      "name": "VAA 攻擊型",
      "pick": "VXUS",
      "assets": [
        "VOO",
        "VXUS",
        "VWO",
        "BND"
      ],
      "mode": "intl",
      "modeLabel": "攻擊模式"
    }
  ],
  "momentum": {
    "title": "加速雙動能 · 騷速雙動能",
    "subtitle": "分數 = avg(1m, 3m, 6m)",
    "rows": [
      {
        "ticker": "VOO",
        "m1": 0.092427,
        "m3": 0.026029,
        "m6": 0.04105,
        "m12": 0.280614,
        "score": 0.053169,
        "winner": false
      },
      {
        "ticker": "QQQ",
        "m1": 0.124173,
        "m3": 0.043385,
        "m6": 0.031443,
        "m12": 0.36465,
        "score": 0.066334,
        "winner": false
      },
      {
        "ticker": "VSS",
        "m1": 0.099115,
        "m3": 0.050754,
        "m6": 0.125597,
        "m12": 0.330676,
        "score": 0.091822,
        "winner": true
      },
      {
        "ticker": "TLT",
        "m1": 0.004383,
        "m3": -0.000689,
        "m6": -0.035663,
        "m12": -0.026825,
        "score": -0.010656,
        "winner": false
      },
      {
        "ticker": "BIL",
        "m1": -0.000982,
        "m3": -0.001091,
        "m6": -0.002289,
        "m12": -0.001853,
        "score": -0.001454,
        "winner": false
      }
    ]
  },
  "vaa": {
    "attack": [
      {
        "ticker": "VOO",
        "score": 1.576,
        "winner": false
      },
      {
        "ticker": "VXUS",
        "score": 1.7946,
        "winner": true
      },
      {
        "ticker": "VWO",
        "score": 1.7919,
        "winner": false
      },
      {
        "ticker": "BND",
        "score": 0.053,
        "winner": false
      }
    ],
    "defense": [
      {
        "ticker": "LQD",
        "score": 0.0941,
        "winner": false
      },
      {
        "ticker": "IEF",
        "score": 0.0407,
        "winner": false
      },
      {
        "ticker": "SHY",
        "score": -0.0207,
        "winner": false
      },
      {
        "ticker": "BIL",
        "score": -0.0226,
        "winner": false
      }
    ],
    "pickLabel": "攻擊模式 · 最強標的",
    "pickReason": "ALL 攻擊資產得分 > 0",
    "pick": "VXUS"
  }
}